smtptester/__init__.py
smtptester/assets/smtptester.png
smtptester/cli.py
smtptester/dns.py
smtptester/gui.py
smtptester/smtp.py
smtptester/util.py
smtptester-1.1.2.dist-info/entry_points.txt
smtptester-1.1.2.dist-info/WHEEL
smtptester-1.1.2.dist-info/METADATA
smtptester-1.1.2.dist-info/RECORD
