Metadata-Version: 2.1
Name: smtptester
Version: 1.1.2
Summary: A graphical and command line SMTP diagnostic tool
Home-page: https://github.com/mconigliaro/smtptester
Author: Mike Conigliaro
Author-email: mike@conigliaro.org
Requires-Python: >=3.8,<3.11
Classifier: Development Status :: 5 - Production/Stable
Classifier: Environment :: Console
Classifier: Environment :: X11 Applications :: Qt
Classifier: Intended Audience :: Information Technology
Classifier: Intended Audience :: System Administrators
Classifier: License :: OSI Approved :: MIT License
Classifier: Natural Language :: English
Classifier: Operating System :: OS Independent
Classifier: Programming Language :: Python :: 3
Classifier: Programming Language :: Python :: 3.10
Classifier: Programming Language :: Python :: 3.8
Classifier: Programming Language :: Python :: 3.9
Classifier: Topic :: Communications :: Email
Classifier: Topic :: System :: Systems Administration
Classifier: Topic :: Utilities
Requires-Dist: dnspython (>=2.2,<3.0)
Requires-Dist: pyside6 (>=6.3,<7.0)
Project-URL: Repository, https://github.com/mconigliaro/smtptester
